{
  "head": {
    "title": "New Candy Wrapper project",
    "link": [
      {
        "rel": "stylesheet",
        "href": "https://fonts.googleapis.com/css2?family=Outfit:wght@300;400;500;600&display=swap",
        "type": "text/css"
      },
      {
        "rel": "stylesheet",
        "href": "https://fonts.googleapis.com/css2?family=Rajdhani:wght@300;400;500;600;700&display=swap",
        "type": "text/css"
      }
    ],
    "meta": [
      {
        "name": "viewport",
        "content": "width=device-width, initial-scale=1.0"
      },
      {
        "charset": "UTF-8"
      },
      {
        "name": "description",
        "content": "New Candy Wrapper project."
      },
      {
        "name": "keywords",
        "content": ""
      }
    ]
  },
  "classroom": [
    {
      "name": "@view-transition",
      "type": "custom",
      "style": "navigation: auto;"
    },
    {
      "name": "h1",
      "type": "element",
      "mediaQueries": [
        {
          "query": "max-width: 640px",
          "style": "font-size: 32px; line-height: 38px;"
        }
      ],
      "style": "font-family: Rajdhani, serif; font-size: 48px; font-weight: 700; letter-spacing: 10px; line-height: 48px; margin: 0; text-align: center; white-space: pre-wrap;"
    }
  ],
  "const": {
    "features": [
      "Automatic CSS generation",
      "Autocompletion",
      "Built-in linting",
      "Preview-based",
      "Dynamic routing",
      "Template building",
      "Global variables"
    ]
  }
}